licomp_hermione/__main__.py
licomp_hermione/config.py
licomp_hermione/hermione.py
licomp_hermione/data/hermione-matrix-DistributionNonSource-Altered.json
licomp_hermione/data/hermione-matrix-DistributionNonSource-Unmodified.json
licomp_hermione/data/hermione-matrix-DistributionSource-Altered.json
licomp_hermione/data/hermione-matrix-DistributionSource-Unmodified.json
licomp_hermione/data/hermione-matrix-InternalUse-Altered.json
licomp_hermione/data/hermione-matrix-InternalUse-Unmodified.json
licomp_hermione/data/hermione-matrix.json
licomp_hermione-0.5.2.dist-info/GPL-3.0-or-later.txt
licomp_hermione-0.5.2.dist-info/METADATA
licomp_hermione-0.5.2.dist-info/WHEEL
licomp_hermione-0.5.2.dist-info/entry_points.txt
licomp_hermione-0.5.2.dist-info/top_level.txt
licomp_hermione-0.5.2.dist-info/RECORD
